AxureRpZhinan/README.md
AxureRpZhinan/__init__.py
AxureRpZhinan/__main__.py
AxureRpZhinan/file.epub
AxureRpZhinan/index.html
AxureRpZhinan/css/__init__.py
AxureRpZhinan/css/annotations.css
AxureRpZhinan/css/main.css
AxureRpZhinan/css/normalize.css
AxureRpZhinan/css/popup.css
AxureRpZhinan/font/__init__.py
AxureRpZhinan/font/fontello.eot
AxureRpZhinan/font/fontello.svg
AxureRpZhinan/font/fontello.ttf
AxureRpZhinan/font/fontello.woff
AxureRpZhinan/img/__init__.py
AxureRpZhinan/img/annotator-glyph-sprite.png
AxureRpZhinan/img/annotator-icon-sprite.png
AxureRpZhinan/img/apple-touch-icon.png
AxureRpZhinan/img/cancelfullscreen.png
AxureRpZhinan/img/close.png
AxureRpZhinan/img/fullscreen.png
AxureRpZhinan/img/loader.gif
AxureRpZhinan/img/menu-icon.png
AxureRpZhinan/img/save.png
AxureRpZhinan/img/saved.png
AxureRpZhinan/img/settings-s.png
AxureRpZhinan/img/settings.png
AxureRpZhinan/img/star.png
AxureRpZhinan/js/__init__.py
AxureRpZhinan/js/epub.js
AxureRpZhinan/js/epub.min.js
AxureRpZhinan/js/epub.min.map
AxureRpZhinan/js/hooks.min.js
AxureRpZhinan/js/hooks.min.map
AxureRpZhinan/js/reader.js
AxureRpZhinan/js/reader.js.map
AxureRpZhinan/js/reader.min.js
AxureRpZhinan/js/reader.min.map
AxureRpZhinan/js/hooks/__init__.py
AxureRpZhinan/js/hooks/extensions/__init__.py
AxureRpZhinan/js/hooks/extensions/highlight.js
AxureRpZhinan/js/libs/__init__.py
AxureRpZhinan/js/libs/jquery.min.js
AxureRpZhinan/js/libs/localforage.min.js
AxureRpZhinan/js/libs/screenfull.js
AxureRpZhinan/js/libs/screenfull.min.js
AxureRpZhinan/js/libs/zip.min.js
AxureRpZhinan/js/plugins/__init__.py
AxureRpZhinan/js/plugins/hypothesis.js
AxureRpZhinan/js/plugins/search.js
axure_rp_zhinan-2024.3.4.0.dist-info/METADATA
axure_rp_zhinan-2024.3.4.0.dist-info/WHEEL
axure_rp_zhinan-2024.3.4.0.dist-info/entry_points.txt
axure_rp_zhinan-2024.3.4.0.dist-info/top_level.txt
axure_rp_zhinan-2024.3.4.0.dist-info/RECORD
